{
  "entry_id": "bakõm_5b96fb5b-7007-416d-a88e-90c0d01888c3",
  "headword": "bakõm",
  "morph_type": "stem",
  "pronunciation": "bakõm",
  "variant_of": null,
  "these_vars": null,
  "note": {
    "bibliography": [
      "encontrado em cartilha 4; lição 13"
    ]
  },
  "sense": {
    "432baa2e-0961-495d-83aa-0cf6031e6f9f": {
      "pos": "?",
      "gloss": {
        "pt": "?"
      },
      "def": {
        "pt": "?"
      },
      "reverse": "",
      "note": "",
      "these_vars": ""
    }
  },
  "date": "2018-03-08T07:17:53Z"
}