{
  "entry_id": "atsóm_02a79639-e72e-482a-98fe-e2a3e76d3f81",
  "headword": "atsóm",
  "morph_type": "stem",
  "pronunciation": "ʔaˈɉ’ɔbm",
  "variant_of": null,
  "these_vars": null,
  "note": {
    "bibliography": "Fieldnotes Epps/Obert; 2018"
  },
  "sense": {
    "4bcb3e10-ba0a-4e58-8984-5b1a542a42f6": {
      "pos": "Verb",
      "gloss": {
        "en": "swim",
        "pt": "nadar"
      },
      "def": {
        "en": "swim",
        "pt": "nadar"
      },
      "reverse": "",
      "note": "",
      "these_vars": ""
    }
  },
  "date": "2018-07-10T23:19:31Z"
}