{
  "Unnamed: 0": 1207,
  "entry_id": "badah_e82440f2-0d44-46ba-b8ba777dbf1a0eb4",
  "bibliography": "SIL Dict 2011",
  "date": "2018-03-08T07:17:52Z",
  "date_modified": "",
  "headword": "badah",
  "morph_type": "stem",
  "note": {
    "Note": "Predicted phonemic form from source Sil Dict 2011."
  },
  "other_sources": "{'Sil Dict 2011': 'badah'}",
  "pronunciation": "badah",
  "sense": {
    "b72bc68e-c154-487d-9fee-2457f25cba60": {
      "pos": "adv",
      "gloss": {
        "pt": "mais.tarde"
      },
      "def": {
        "pt": "mais tarde (hoje)"
      },
      "reverse": "",
      "note": "",
      "these_vars": "{'bada_3607fbf6-6d6b-4cfd-92a8-0ba96e99f2ff': {'type': '_component-lexeme', 'variant-type': 'Unspecified Variant'}}"
    }
  },
  "these_vars": {},
  "variant_of": {},
  "ipa": "badah"
}