{
  "headword": "barajaa",
  "entry_id": "barajaa2_e50cdd50-e263-4c36-8427-a1576df4ce0c",
  "morph_type": "stem",
  "pronunciation": "baɾaja:ʔ",
  "variant": null,
  "note": null,
  "sense": [
    {
      "sense_id": "2b320773-7e31-4ce3-aa9c-e3bcc6ce5912",
      "pos": "Noun",
      "gloss": {
        "en": "avocado",
        "pt": "abacate"
      },
      "def": {
        "en": "avocado",
        "pt": "abacate"
      },
      "reverse": "",
      "note": "",
      "var_of_sense": {}
    }
  ],
  "date": "2019-01-14T03:46:55Z"
}