{
  "Unnamed: 0": 680,
  "entry_id": "dapuuh_e2fa23b4-ba19-43c9-bbbb-954097c46f42",
  "bibliography": "Fieldnotes Epps/Obert; 2018",
  "date": "2018-07-10T23:18:37Z",
  "date_modified": "",
  "headword": "dapuuh",
  "morph_type": "stem",
  "note": {},
  "other_sources": "",
  "pronunciation": "daˈpu:h",
  "sense": {
    "0ab4eeb0-d256-4a06-a0c1-9bcbe90ba9e0": {
      "pos": "Verb",
      "gloss": {
        "en": "swell",
        "pt": "inchar"
      },
      "def": {
        "en": "swell",
        "pt": "inchar"
      },
      "reverse": "",
      "note": "",
      "these_vars": ""
    }
  },
  "these_vars": null,
  "variant_of": {},
  "ipa": "dapu:h"
}