{
  "entry_id": "datés_d4d8658e-0692-4022-8f66-d7ff445c29c8",
  "headword": "datés",
  "morph_type": "stem",
  "pronunciation": "daˈtɛʃ]",
  "variant_of": null,
  "these_vars": null,
  "note": {},
  "sense": {
    "d0178027-9a04-4739-8553-10b961b353eb": {
      "pos": "adj?",
      "gloss": {
        "en": "painful",
        "pt": "doloroso"
      },
      "def": {
        "en": "painful",
        "pt": "doloroso"
      },
      "reverse": "",
      "note": "",
      "these_vars": ""
    }
  },
  "date": "2018-07-07T17:58:14Z",
  "bibliography": "Fieldnotes Epps/Obert; 2018"
}