{
  "headword": "gabok",
  "entry_id": "gabok_9288536e-4047-4b13-aedb-1a10b207ea07",
  "morph_type": "stem",
  "pronunciation": "gabok",
  "variant": null,
  "note": [
    [
      "cartilha 4; lição 4",
      "bibliography"
    ]
  ],
  "sense": [
    {
      "sense_id": "282db821-28d3-43a6-bfd5-5f739c562939",
      "pos": "v?",
      "gloss": {
        "pt": "?"
      },
      "def": {
        "pt": "?"
      },
      "reverse": "",
      "note": "",
      "var_of_sense": {}
    }
  ],
  "date": "2018-03-26T16:29:15Z"
}