{
  "entry_id": "hajaar_8214f460-f0df-4453-97a7-9b50fa6d0cb4",
  "headword": "hajaar",
  "morph_type": "stem",
  "pronunciation": "haˈja:ɾǝ",
  "variant_of": null,
  "these_vars": null,
  "note": {},
  "sense": {
    "cd6b8162-97b0-43ac-b876-69675eeaa301": {
      "pos": "Noun",
      "gloss": {
        "en": "amazon.dolphin",
        "pt": "boto"
      },
      "def": {
        "en": "amazon.dolphin",
        "pt": "boto"
      },
      "reverse": "",
      "note": "",
      "these_vars": ""
    }
  },
  "date": "2018-07-27T23:09:15Z",
  "bibliography": "Fieldnotes Epps/Obert; 2018"
}