{
  "entry_id": "hõm_4a712cc3-64f7-4370-a6978992d4110af6",
  "headword": "hõm",
  "morph_type": "root",
  "pronunciation": "hõm",
  "variant_of": {},
  "these_vars": {},
  "note": {
    "Note": "Predicted phonemic form from source Cartilhas."
  },
  "sense": {
    "f8004460-d3fe-4c66-bf50-ba9eba0950ee": {
      "pos": "?",
      "gloss": {
        "pt": "?"
      },
      "def": {
        "pt": "?"
      },
      "reverse": "",
      "note": "",
      "these_vars": ""
    }
  },
  "date": "2018-03-08T07:17:53Z",
  "bibliography": "encontrado na cartilha 4; lição 7",
  "other_sources": "{'Cartilhas': 'hõm'}"
}