{
  "entry_id": "hỹỹ_fee5a672-b4ee-4f11-a91a-ddb6298bf761",
  "﻿headword": "hỹỹ",
  "morph_type": "stem",
  "pronunciation": "hɨ̃:",
  "variant_of": null,
  "these_vars": {
    "hỹ_ed75fc76-6ba5-45fa-9836-fcd4fd502dd0": {
      "﻿headword": "hỹ",
      "morph_type": "stem",
      "pronunciation": "hɨ̃",
      "these_vars": null,
      "note": [
        [
          "SIL 2011",
          "bibliography"
        ]
      ],
      "sense": null,
      "date": "2018-03-22T21:19:31Z",
      "var_type": [
        "Unspecified Variant"
      ]
    }
  },
  "note": [
    [
      "encontrado em cartilha 4; lição 14",
      "bibliography"
    ]
  ],
  "sense": {
    "4713b0d1-e327-4b22-a41b-7db7430fe70e": {
      "pos": "par?",
      "gloss": {
        "pt": "?"
      },
      "def": {
        "pt": "?"
      },
      "reverse": "",
      "note": "",
      "these_vars": ""
    }
  },
  "date": "2018-03-22T21:18:02Z"
}