{
  "headword": "jarana",
  "entry_id": "jarana2_bd32e479-6d6f-4eb6-9231-117817f4d9e0",
  "morph_type": "stem",
  "pronunciation": "jaɾadnãʔ",
  "variant": null,
  "note": null,
  "sense": [
    {
      "sense_id": "90264752-e438-4aea-80d1-8a33152fd555",
      "pos": "Noun",
      "gloss": {
        "en": "moriche palm sprout",
        "pt": "grelo de buriti"
      },
      "def": {
        "en": "moriche palm sprout (used for making hammocks)",
        "pt": "grelo de buriti (de que se faz rede)"
      },
      "reverse": null,
      "note": null,
      "var_of_sense": []
    }
  ],
  "date": "2019-01-14T03:46:55Z"
}