{
  "headword": "karatu",
  "entry_id": "karatu_5a0df1f2-ad66-44d9-8b7e-ebb5d37aee27",
  "morph_type": "stem",
  "pronunciation": null,
  "variant": null,
  "note": [
    [
      "Fieldnotes Epps/Obert; 2018",
      "bibliography"
    ]
  ],
  "sense": [
    {
      "sense_id": "73f7e406-6f01-44da-81c6-8fc549a1bdf5",
      "pos": "Noun",
      "gloss": {
        "en": "parrot",
        "pt": "papagaio"
      },
      "def": {
        "en": "parrot",
        "pt": "papagaio"
      },
      "reverse": null,
      "note": null,
      "var_of_sense": []
    }
  ],
  "date": "2018-07-27T20:31:26Z"
}