{
  "Unnamed: 0": 255,
  "entry_id": "masäk_53f6205b-cb80-42ad-82da-874ffdd862c4",
  "bibliography": "Fieldnotes Epps/Obert; 2018",
  "date": "2018-07-27T20:21:21Z",
  "date_modified": "",
  "headword": "masäk",
  "morph_type": "stem",
  "note": {},
  "other_sources": "",
  "pronunciation": "",
  "sense": {
    "c9b2de3b-c6d7-4412-b17a-281857187ec9": {
      "pos": "Noun",
      "gloss": {
        "en": "gray-winged Trumpeter",
        "pt": "jacamim"
      },
      "def": {
        "en": "gray-winged Trumpeter",
        "pt": "jacamim"
      },
      "reverse": "",
      "note": "",
      "these_vars": ""
    }
  },
  "these_vars": null,
  "variant_of": {},
  "ipa": "maʃʌk"
}