{
  "headword": "matug",
  "entry_id": "matug_4ea45a05-e572-439d-a59d-3e3dd960ec0f",
  "morph_type": "stem",
  "pronunciation": "maˈtug˺",
  "variant": null,
  "note": [
    [
      "Fieldnotes Epps/Obert; 2018z",
      "bibliography"
    ]
  ],
  "sense": [
    {
      "sense_id": "d85f760c-86aa-4633-8737-4733b853423f",
      "pos": "Noun",
      "gloss": {
        "en": "tortoise",
        "pt": "jabuti"
      },
      "def": {
        "en": "tortoise",
        "pt": "jabuti"
      },
      "reverse": null,
      "note": null,
      "var_of_sense": []
    }
  ]
}