{
  "headword": "mehëëm doo",
  "entry_id": "mehëëm doo_bfd36b12-009d-4741-aa26-24642c4403ca",
  "morph_type": "phrase",
  "pronunciation": "mẽhə:bm do:ʔ",
  "variant": null,
  "note": null,
  "sense": [
    {
      "sense_id": "1b3de5e7-5978-487c-9201-aad5e9e3d093",
      "pos": "Noun",
      "gloss": {
        "en": "healer",
        "pt": "benzador"
      },
      "def": {
        "en": "healer",
        "pt": "benzador; curandeiro; kumu (Tukano)"
      },
      "reverse": null,
      "note": null,
      "var_of_sense": []
    }
  ],
  "date": "2019-01-14T03:46:55Z"
}