{
  "headword": "moo nʹaa kawʹaat",
  "entry_id": "moo nʹaa kawʹaat_82d0dccc-bff7-4bfb-802a-812407c55172",
  "morph_type": "root",
  "pronunciation": "mo: na̰: kawa̰:t",
  "variant": null,
  "note": [
    [
      "SIL 2011",
      "bibliography"
    ]
  ],
  "sense": [
    {
      "sense_id": "61bb1e24-6231-443a-ba04-ad4062d25ca9",
      "pos": "v",
      "gloss": {
        "pt": "fazer.ligeiro"
      },
      "def": {
        "pt": "fazer ligeiro"
      },
      "reverse": null,
      "note": null,
      "var_of_sense": []
    }
  ]
}