{
  "Unnamed: 0": 954,
  "entry_id": "ra_691deaf6-11ec-4636-828c82636a8e4ead",
  "bibliography": "Weir 1990 (la)",
  "date": "2018-03-22T17:13:55Z",
  "date_modified": "",
  "headword": "ra",
  "morph_type": "stem",
  "note": {
    "Note": "Predicted phonemic form from source Weir."
  },
  "other_sources": "{'Weir': 'ra'}",
  "pronunciation": "ra",
  "sense": {
    "6704bbec-ab67-4664-8cc6-dccf621623a7": {
      "pos": "pre",
      "gloss": {
        "en": "3PL",
        "pt": "3PL"
      },
      "def": {
        "en": "they",
        "pt": "eles"
      },
      "reverse": "",
      "note": "",
      "these_vars": ""
    }
  },
  "these_vars": {},
  "variant_of": {},
  "ipa": "ra"
}