{
  "entry_id": "sëëw_7c511834-586a-456c-884a-02fda6ccd6aa",
  "﻿headword": "sëëw",
  "morph_type": "stem",
  "pronunciation": "ʃə:w",
  "variant_of": null,
  "these_vars": {
    "ʃɤːw_009b3e07-21aa-4c01-aeda-2447f5bc3e94": {
      "﻿headword": "ʃɤːw",
      "morph_type": "stem",
      "pronunciation": "",
      "these_vars": null,
      "note": null,
      "sense": {
        "2e7ced09-86a7-4ad6-a7a0-e36f9523d65a": {
          "pos": "Noun",
          "gloss": {
            "en": "pajé (pl sɤ̰ːw)"
          },
          "def": null,
          "reverse": "",
          "note": "",
          "these_vars": ""
        }
      },
      "date": "2018-06-20T05:09:53Z",
      "var_type": "Martins"
    }
  },
  "note": null,
  "sense": {
    "5ccc7fd8-e6aa-432b-b538-67270ef1447d": {
      "pos": "Noun",
      "gloss": {
        "en": "shaman",
        "pt": "xaman"
      },
      "def": {
        "en": "shaman",
        "pt": "xaman; pajé; feiticeiro"
      },
      "reverse": "",
      "note": "",
      "these_vars": ""
    }
  },
  "date": "2019-01-14T03:46:55Z"
}