{
  "entry_id": "ta=bóg_ffd05df4-c222-4abc-9780-d5e06413c1f1",
  "headword": "ta=bóg",
  "morph_type": "stem",
  "pronunciation": "bɔg˺",
  "variant_of": null,
  "these_vars": null,
  "note": {},
  "sense": {
    "3469ae1b-cc4e-4316-8f5b-f6ad6e92225f": {
      "pos": "Noun",
      "gloss": {
        "en": "bark",
        "pt": "casca"
      },
      "def": {
        "en": "bark",
        "pt": "casca"
      },
      "reverse": "",
      "note": "",
      "these_vars": ""
    }
  },
  "date": "2018-03-08T07:17:53Z",
  "bibliography": "Fieldnotes Epps/Obert; 2018"
}