{
  "entry_id": "tatuɟ_95665b00-9d5a-441d-9b43-a1c6000ebd62",
  "﻿headword": "tatuɟ",
  "morph_type": "stem",
  "pronunciation": "",
  "variant_of": null,
  "these_vars": {
    "tuɟ_1f099057-c3de-482b-9a51-6994e7b74391": {
      "﻿headword": "tuɟ",
      "morph_type": "stem",
      "pronunciation": "",
      "these_vars": null,
      "note": null,
      "sense": {
        "c7a2c4a8-ff89-487f-864a-c17e145afd69": {
          "pos": "Noun",
          "gloss": {
            "en": "espécie de formiga"
          },
          "def": null,
          "reverse": "",
          "note": "",
          "these_vars": ""
        }
      },
      "date": "2018-06-20T05:09:53Z",
      "var_type": "Martins"
    }
  },
  "note": null,
  "sense": {
    "466da06d-5775-4881-b966-e11273a46f0e": {
      "pos": "Noun",
      "gloss": {
        "en": "espécie de formiga"
      },
      "def": null,
      "reverse": "",
      "note": "",
      "these_vars": ""
    }
  },
  "date": "2018-06-20T05:09:53Z"
}