{
  "entry_id": "tũũh_1b11b954-a8f9-47e3-8041-e7ad344c4fb6",
  "﻿headword": "tũũh",
  "morph_type": "stem",
  "pronunciation": "tũ:h",
  "variant_of": null,
  "these_vars": {
    "tũũ_3b535375-c8fc-4f63-bb26-128f9d1c478f": {
      "﻿headword": "tũũ",
      "morph_type": "stem",
      "pronunciation": "tũ:",
      "these_vars": null,
      "note": [
        [
          "encontrado em cartilha 4; lição 16",
          "bibliography"
        ]
      ],
      "sense": null,
      "date": "2018-03-23T14:42:33Z",
      "var_type": [
        "Unspecified Variant"
      ]
    }
  },
  "note": [
    [
      "SIL 2011",
      "bibliography"
    ]
  ],
  "sense": {
    "d69496ab-5a91-4287-91a7-69f70883fabb": {
      "pos": "adv",
      "gloss": {
        "pt": "no.chão"
      },
      "def": {
        "pt": "no chão"
      },
      "reverse": "",
      "note": "",
      "these_vars": ""
    }
  },
  "date": "2018-03-08T07:17:53Z"
}