{
  "headword": "wawët",
  "entry_id": "wawët_135af2d2-bd6b-445c-a1ed-837cb137c40d",
  "morph_type": "stem",
  "pronunciation": "",
  "variant_of": null,
  "these_vars": "",
  "note": [
    [
      "Fieldnotes Epps/Obert; 2018",
      "bibliography"
    ]
  ],
  "sense": {
    "514fe7a9-a793-47a1-a7ee-0d2b60c0c376": {
      "pos": "Noun",
      "gloss": {
        "en": "wild.dog",
        "pt": "cachorro.do.mato"
      },
      "def": {
        "en": "wild dog",
        "pt": "cachorro do mato"
      },
      "reverse": "",
      "note": "",
      "these_vars": ""
    }
  },
  "date": "2018-07-27T20:47:32Z"
}