{
  "entry_id": "ʃĩ:n_bef46c0d-3efb-4cc7-b2c41a829fc17d97",
  "headword": "ʃĩ:n",
  "morph_type": "stem",
  "pronunciation": "ʃĩ:n",
  "variant_of": {},
  "these_vars": {},
  "note": {
    "Note": "Predicted phonemic form from source Sil Dict 2011."
  },
  "sense": {
    "7693b61a-ed61-4709-9cf5-037de32b820f": {
      "pos": "n",
      "gloss": {
        "pt": "coral"
      },
      "def": {
        "pt": "esp. de cobra (coral)"
      },
      "reverse": "",
      "note": "",
      "these_vars": ""
    }
  },
  "date": "2018-03-08T07:17:53Z",
  "bibliography": "SIL Dict 2011",
  "other_sources": "{'Barbosa': 'ʃĩːn', 'Sil Dict 2011': 'sĩĩn'}"
}