{
  "headword": "ỹỹn",
  "entry_id": "ỹỹn2_cd68549e-1a6e-4765-94fe-b4d379bdf417",
  "morph_type": "stem",
  "pronunciation": "ʔɨ̃:n",
  "variant": null,
  "note": null,
  "sense": [
    {
      "sense_id": "5a55c287-aeca-4488-8237-2c9306007e96",
      "pos": "Noun",
      "gloss": {
        "en": "mother",
        "pt": "mãe"
      },
      "def": {
        "en": "mother",
        "pt": "mãe"
      },
      "reverse": "",
      "note": "",
      "var_of_sense": {}
    }
  ],
  "date": "2019-01-14T03:46:56Z"
}